Workbook

Sheet Resumen
A1: MAD ESTUDIO · Cuenta corriente Bahioma
A2: Resumen automático. No se edita: todo se calcula a partir de las hojas Movimientos y Cobros.
A3: Año del resumen mensual → | B3: 2026
A4: ESTADO DE CUENTA
A5: Total cobrado a Bahioma (cheques/transf. acreditados) | B5: =SUMIFS(Cobros!$F$4:$F$303,Cobros!$H$4:$H$303,"Cobrado") -> 5684230
A6: Por acreditar (cheques en cartera) | B6: =SUMIFS(Cobros!$F$4:$F$303,Cobros!$H$4:$H$303,"En cartera") -> 2920000
A7: Aplicado a cuenta corriente (movimientos saldados con CC) | B7: =SUMIFS(Movimientos!$H$4:$H$303,Movimientos!$I$4:$I$303,"CC",Movimientos!$J$4:$J$303,"Saldado") -> 5824194.1
A8: SALDO CUENTA CORRIENTE (+ a favor de Bahioma / − a favor de MAD) | B8: =B5-B7 -> -139964.06
A9: Pagado por transferencia / efectivo (fuera de la CC) | B9: =SUMIFS(Movimientos!$H$4:$H$303,Movimientos!$J$4:$J$303,"Saldado")-B7 -> 2224506.4
A10: Pendiente de pago (movimientos con estado Pendiente) | B10: =SUMIFS(Movimientos!$H$4:$H$303,Movimientos!$J$4:$J$303,"Pendiente") -> 1223080.7
A11: Saldo proyectado (saldo CC + cheques en cartera − pendientes) | B11: =B8+B6-B10 -> 1556955.2
A12: IVA facturado acumulado | B12: =SUM(Movimientos!$G$4:$G$303) -> 386071.35
A13: Impuesto al cheque informado (no afecta la CC) | B13: =SUM(Cobros!$G$4:$G$303) -> 0
A14: Lectura del saldo: positivo = Bahioma tiene plata a favor en la CC; negativo = Bahioma le debe ese monto a MAD ESTUDIO. El proyectado supone que los cheques en cartera se acreditan y los pendientes se descuentan de la CC.
A16: COSTO MENSUAL POR CONCEPTO
A17: Mes | B17: Año | D17: DO (cargas) | E17: Honorarios | F17: Otros | G17: Total
A18: Enero | B18: =$B$3 -> 2026 | D18: =SUMIFS(Movimientos!$H$4:$H$303,Movimientos!$B$4:$B$303,$A18,Movimientos!$C$4:$C$303,"DO (cargas)",Movimientos!$A$4:$A$303,$B18) -> 0 | E18: =SUMIFS(Movimientos!$H$4:$H$303,Movimientos!$B$4:$B$303,$A18,Movimientos!$C$4:$C$303,"Honorarios",Movimientos!$A$4:$A$303,$B18) -> 0 | F18: =SUMIFS(Movimientos!$H$4:$H$303,Movimientos!$B$4:$B$303,$A18,Movimientos!$C$4:$C$303,"Otros",Movimientos!$A$4:$A$303,$B18) -> 0 | G18: =SUM(D18:F18) -> 0
A19: Febrero | B19: =$B$3 -> 2026 | D19: =SUMIFS(Movimientos!$H$4:$H$303,Movimientos!$B$4:$B$303,$A19,Movimientos!$C$4:$C$303,"DO (cargas)",Movimientos!$A$4:$A$303,$B19) -> 0 | E19: =SUMIFS(Movimientos!$H$4:$H$303,Movimientos!$B$4:$B$303,$A19,Movimientos!$C$4:$C$303,"Honorarios",Movimientos!$A$4:$A$303,$B19) -> 0 | F19: =SUMIFS(Movimientos!$H$4:$H$303,Movimientos!$B$4:$B$303,$A19,Movimientos!$C$4:$C$303,"Otros",Movimientos!$A$4:$A$303,$B19) -> 0 | G19: =SUM(D19:F19) -> 0
A20: Marzo | B20: =$B$3 -> 2026 | D20: =SUMIFS(Movimientos!$H$4:$H$303,Movimientos!$B$4:$B$303,$A20,Movimientos!$C$4:$C$303,"DO (cargas)",Movimientos!$A$4:$A$303,$B20) -> 0 | E20: =SUMIFS(Movimientos!$H$4:$H$303,Movimientos!$B$4:$B$303,$A20,Movimientos!$C$4:$C$303,"Honorarios",Movimientos!$A$4:$A$303,$B20) -> 0 | F20: =SUMIFS(Movimientos!$H$4:$H$303,Movimientos!$B$4:$B$303,$A20,Movimientos!$C$4:$C$303,"Otros",Movimientos!$A$4:$A$303,$B20) -> 0 | G20: =SUM(D20:F20) -> 0
A21: Abril | B21: =$B$3 -> 2026 | D21: =SUMIFS(Movimientos!$H$4:$H$303,Movimientos!$B$4:$B$303,$A21,Movimientos!$C$4:$C$303,"DO (cargas)",Movimientos!$A$4:$A$303,$B21) -> 0 | E21: =SUMIFS(Movimientos!$H$4:$H$303,Movimientos!$B$4:$B$303,$A21,Movimientos!$C$4:$C$303,"Honorarios",Movimientos!$A$4:$A$303,$B21) -> 0 | F21: =SUMIFS(Movimientos!$H$4:$H$303,Movimientos!$B$4:$B$303,$A21,Movimientos!$C$4:$C$303,"Otros",Movimientos!$A$4:$A$303,$B21) -> 0 | G21: =SUM(D21:F21) -> 0
A22: Mayo | B22: =$B$3 -> 2026 | D22: =SUMIFS(Movimientos!$H$4:$H$303,Movimientos!$B$4:$B$303,$A22,Movimientos!$C$4:$C$303,"DO (cargas)",Movimientos!$A$4:$A$303,$B22) -> 0 | E22: =SUMIFS(Movimientos!$H$4:$H$303,Movimientos!$B$4:$B$303,$A22,Movimientos!$C$4:$C$303,"Honorarios",Movimientos!$A$4:$A$303,$B22) -> 0 | F22: =SUMIFS(Movimientos!$H$4:$H$303,Movimientos!$B$4:$B$303,$A22,Movimientos!$C$4:$C$303,"Otros",Movimientos!$A$4:$A$303,$B22) -> 0 | G22: =SUM(D22:F22) -> 0
A23: Junio | B23: =$B$3 -> 2026 | D23: =SUMIFS(Movimientos!$H$4:$H$303,Movimientos!$B$4:$B$303,$A23,Movimientos!$C$4:$C$303,"DO (cargas)",Movimientos!$A$4:$A$303,$B23) -> 2224506.4 | E23: =SUMIFS(Movimientos!$H$4:$H$303,Movimientos!$B$4:$B$303,$A23,Movimientos!$C$4:$C$303,"Honorarios",Movimientos!$A$4:$A$303,$B23) -> 0 | F23: =SUMIFS(Movimientos!$H$4:$H$303,Movimientos!$B$4:$B$303,$A23,Movimientos!$C$4:$C$303,"Otros",Movimientos!$A$4:$A$303,$B23) -> 0 | G23: =SUM(D23:F23) -> 2224506.4
A24: Julio | B24: =$B$3 -> 2026 | D24: =SUMIFS(Movimientos!$H$4:$H$303,Movimientos!$B$4:$B$303,$A24,Movimientos!$C$4:$C$303,"DO (cargas)",Movimientos!$A$4:$A$303,$B24) -> 1379842 | E24: =SUMIFS(Movimientos!$H$4:$H$303,Movimientos!$B$4:$B$303,$A24,Movimientos!$C$4:$C$303,"Honorarios",Movimientos!$A$4:$A$303,$B24) -> 0 | F24: =SUMIFS(Movimientos!$H$4:$H$303,Movimientos!$B$4:$B$303,$A24,Movimientos!$C$4:$C$303,"Otros",Movimientos!$A$4:$A$303,$B24) -> 0 | G24: =SUM(D24:F24) -> 1379842
A25: Agosto | B25: =$B$3 -> 2026 | D25: =SUMIFS(Movimientos!$H$4:$H$303,Movimientos!$B$4:$B$303,$A25,Movimientos!$C$4:$C$303,"DO (cargas)",Movimientos!$A$4:$A$303,$B25) -> 1444352 | E25: =SUMIFS(Movimientos!$H$4:$H$303,Movimientos!$B$4:$B$303,$A25,Movimientos!$C$4:$C$303,"Honorarios",Movimientos!$A$4:$A$303,$B25) -> 1500000 | F25: =SUMIFS(Movimientos!$H$4:$H$303,Movimientos!$B$4:$B$303,$A25,Movimientos!$C$4:$C$303,"Otros",Movimientos!$A$4:$A$303,$B25) -> 0 | G25: =SUM(D25:F25) -> 2944352
A26: Septiembre | B26: =$B$3 -> 2026 | D26: =SUMIFS(Movimientos!$H$4:$H$303,Movimientos!$B$4:$B$303,$A26,Movimientos!$C$4:$C$303,"DO (cargas)",Movimientos!$A$4:$A$303,$B26) -> 1223080.7 | E26: =SUMIFS(Movimientos!$H$4:$H$303,Movimientos!$B$4:$B$303,$A26,Movimientos!$C$4:$C$303,"Honorarios",Movimientos!$A$4:$A$303,$B26) -> 1500000 | F26: =SUMIFS(Movimientos!$H$4:$H$303,Movimientos!$B$4:$B$303,$A26,Movimientos!$C$4:$C$303,"Otros",Movimientos!$A$4:$A$303,$B26) -> 0 | G26: =SUM(D26:F26) -> 2723080.7
A27: Octubre | B27: =$B$3 -> 2026 | D27: =SUMIFS(Movimientos!$H$4:$H$303,Movimientos!$B$4:$B$303,$A27,Movimientos!$C$4:$C$303,"DO (cargas)",Movimientos!$A$4:$A$303,$B27) -> 0 | E27: =SUMIFS(Movimientos!$H$4:$H$303,Movimientos!$B$4:$B$303,$A27,Movimientos!$C$4:$C$303,"Honorarios",Movimientos!$A$4:$A$303,$B27) -> 0 | F27: =SUMIFS(Movimientos!$H$4:$H$303,Movimientos!$B$4:$B$303,$A27,Movimientos!$C$4:$C$303,"Otros",Movimientos!$A$4:$A$303,$B27) -> 0 | G27: =SUM(D27:F27) -> 0
A28: Noviembre | B28: =$B$3 -> 2026 | D28: =SUMIFS(Movimientos!$H$4:$H$303,Movimientos!$B$4:$B$303,$A28,Movimientos!$C$4:$C$303,"DO (cargas)",Movimientos!$A$4:$A$303,$B28) -> 0 | E28: =SUMIFS(Movimientos!$H$4:$H$303,Movimientos!$B$4:$B$303,$A28,Movimientos!$C$4:$C$303,"Honorarios",Movimientos!$A$4:$A$303,$B28) -> 0 | F28: =SUMIFS(Movimientos!$H$4:$H$303,Movimientos!$B$4:$B$303,$A28,Movimientos!$C$4:$C$303,"Otros",Movimientos!$A$4:$A$303,$B28) -> 0 | G28: =SUM(D28:F28) -> 0
A29: Diciembre | B29: =$B$3 -> 2026 | D29: =SUMIFS(Movimientos!$H$4:$H$303,Movimientos!$B$4:$B$303,$A29,Movimientos!$C$4:$C$303,"DO (cargas)",Movimientos!$A$4:$A$303,$B29) -> 0 | E29: =SUMIFS(Movimientos!$H$4:$H$303,Movimientos!$B$4:$B$303,$A29,Movimientos!$C$4:$C$303,"Honorarios",Movimientos!$A$4:$A$303,$B29) -> 0 | F29: =SUMIFS(Movimientos!$H$4:$H$303,Movimientos!$B$4:$B$303,$A29,Movimientos!$C$4:$C$303,"Otros",Movimientos!$A$4:$A$303,$B29) -> 0 | G29: =SUM(D29:F29) -> 0
A30: Total año | D30: =SUM(D18:D29) -> 6271781.2 | E30: =SUM(E18:E29) -> 3000000 | F30: =SUM(F18:F29) -> 0 | G30: =SUM(G18:G29) -> 9271781.2

Sheet Movimientos
A1: Movimientos · lo que Bahioma le debe a MAD ESTUDIO
A2: Una fila por concepto y mes. Columnas en azul = se cargan a mano · Importe (gris) = fórmula Neto + IVA, no editar.
A3: Año | B3: Mes | C3: Concepto | D3: Vencimiento | E3: Factura N° | F3: Neto | G3: IVA | H3: Importe | I3: Forma de pago | J3: Estado | K3: Fecha de pago | L3: Observaciones
A4: 2026 | B4: Junio | C4: DO (cargas) | D4: 1 al 10 de Julio | E4: 147 | F4: 1838435 | G4: 386071.35 | H4: =IF(AND(F4="",G4=""),"",N(F4)+N(G4)) -> 2224506.4 | I4: Transferencia | J4: Saldado | K4: 46237 | L4: Facturado con IVA
A5: 2026 | B5: Julio | C5: DO (cargas) | D5: 1 al 10 de Agosto | F5: 1379842 | H5: =IF(AND(F5="",G5=""),"",N(F5)+N(G5)) -> 1379842 | I5: CC | J5: Saldado | K5: 46249
A6: 2026 | B6: Agosto | C6: DO (cargas) | D6: 1 al 10 de Septiembre | F6: 1444352 | H6: =IF(AND(F6="",G6=""),"",N(F6)+N(G6)) -> 1444352 | I6: CC | J6: Saldado | K6: 46249
A7: 2026 | B7: Agosto | C7: Honorarios | D7: 1 al 10 de Agosto | F7: 1500000 | H7: =IF(AND(F7="",G7=""),"",N(F7)+N(G7)) -> 1500000 | I7: CC | J7: Saldado | K7: 46249
A8: 2026 | B8: Septiembre | C8: DO (cargas) | D8: 1 al 10 de Octubre | F8: 1223080.7 | H8: =IF(AND(F8="",G8=""),"",N(F8)+N(G8)) -> 1223080.7 | J8: Pendiente
A9: 2026 | B9: Septiembre | C9: Honorarios | D9: 1 al 10 de Septiembre | F9: 1500000 | H9: =IF(AND(F9="",G9=""),"",N(F9)+N(G9)) -> 1500000 | I9: CC | J9: Saldado | K9: 46249
H10: =IF(AND(F10="",G10=""),"",N(F10)+N(G10))
H11: =IF(AND(F11="",G11=""),"",N(F11)+N(G11))
H12: =IF(AND(F12="",G12=""),"",N(F12)+N(G12))
H13: =IF(AND(F13="",G13=""),"",N(F13)+N(G13))
H14: =IF(AND(F14="",G14=""),"",N(F14)+N(G14))
H15: =IF(AND(F15="",G15=""),"",N(F15)+N(G15))
H16: =IF(AND(F16="",G16=""),"",N(F16)+N(G16))
H17: =IF(AND(F17="",G17=""),"",N(F17)+N(G17))
H18: =IF(AND(F18="",G18=""),"",N(F18)+N(G18))
H19: =IF(AND(F19="",G19=""),"",N(F19)+N(G19))
H20: =IF(AND(F20="",G20=""),"",N(F20)+N(G20))
H21: =IF(AND(F21="",G21=""),"",N(F21)+N(G21))
... H303: =IF(AND(F303="",G303=""),"",N(F303)+N(G303))

Sheet Cobros
A1: Cobros · plata que entró de Bahioma
A2: Cheques, eCheqs y transferencias recibidas. Solo los cobros en estado Cobrado suman crédito en la cuenta corriente.
A3: Fecha | B3: Banco | C3: Tipo | D3: Número | E3: Fecha de cobro | F3: Importe | G3: Imp. al cheque | H3: Estado | I3: Observaciones
A4: 46219 | B4: Provincia | C4: eCheq | D4: 10533604 | E4: 46249 | F4: 5684230 | H4: Cobrado
A5: 46185 | B5: Credicoop | C5: Cheque | D5: 91419581 | E5: 46285 | F5: 1750000 | H5: En cartera
A6: 46224 | B6: BBVA | C6: Cheque | D6: 734012 | E6: 46286 | F6: 870000 | H6: En cartera
A7: 46198 | B7: Santander | C7: Cheque | D7: 1600101 | E7: 46290 | F7: 300000 | H7: En cartera

Sheet Cómo usar
A1: Cómo usar esta planilla
A2: Es la única fuente de datos del dashboard que ve Bahioma.
B4: 1. Movimientos
B5: Cada vez que haya algo para cobrarle a Bahioma (cargas sociales, honorarios, otro concepto), agregá una fila.
B6: Cargá Año, Mes del servicio, Concepto, Vencimiento (ej. "1 al 10 de Octubre"), Neto y, si emitiste factura, N° e IVA. El Importe se calcula solo.
B7: Mientras no se pague, Estado = Pendiente. Cuando se salde: Estado = Saldado, Fecha de pago y Forma de pago.
B8: Forma de pago CC = se descuenta del crédito de la cuenta corriente. Transferencia / Efectivo = lo pagaron aparte, no toca la CC.
B10: 2. Cobros
B11: Cada cheque, eCheq o transferencia que recibas de Bahioma va en una fila, con su fecha de emisión y fecha de cobro.
B12: Estado En cartera mientras no se acredite; Cobrado cuando entra la plata. Solo los Cobrados suman crédito en la CC.
B13: Imp. al cheque es informativo (lo absorbe MAD) y no se descuenta del crédito.
B15: 3. Resumen
B16: Se calcula solo. Saldo CC = cobros acreditados − movimientos saldados con CC. Positivo: Bahioma tiene plata a favor; negativo: le debe a MAD.
B17: Saldo proyectado = saldo CC + cheques en cartera − movimientos pendientes: cómo queda la cuenta cuando se acrediten los cheques y se apliquen los vencimientos abiertos.
... B23: Reglas para que la importación no falle: no cambies los nombres de las hojas ni de las columnas; usá los valores de las listas desplegables; no dejes filas vacías entre datos.
